RaTEScore/__init__.py
RaTEScore/score.py
RaTEScore/scorer.py
RaTEScore/utils.py
RaTEScore-0.6.0.dist-info/LICENSE
RaTEScore-0.6.0.dist-info/METADATA
RaTEScore-0.6.0.dist-info/WHEEL
RaTEScore-0.6.0.dist-info/top_level.txt
RaTEScore-0.6.0.dist-info/RECORD
