Metadata-Version: 2.1
Name: RaTEScore
Version: 0.6.0
Summary: A Metric for Entity-Aware Radiology Report Generation
Home-page: https://github.com/Angelakeke/RaTEScore
Author: Weike_Zhao
Author-email: zwk0629@sjtu.edu.cn
License: UNKNOWN
Platform: UNKNOWN
License-File: LICENSE
